{
  "schemaVersion": 1,
  "id": "chatstack",
  "version": "${version}",
  "name": "ChatStack",
  "description": "Chat message stacking",
  "authors": [
    "betterclient"
  ],
  "contact": {},
  "license": "MIT",
  "environment": "client",
  "entrypoints": {
    "client": [
      "io.github.betterclient.chatstack.ChatStack"
    ]
  },
  "mixins": [
    "chatstack.mixins.json"
  ],
  "depends": {
    "fabricloader": ">=${loader_version}",
    "fabric": "*",
    "minecraft": "${minecraft_version}"
  }
}
